[
    {
        "Symbol": "TWNKW",
        "Security Name": "Hostess Brands, Inc Wts",
        "Market Category": "R",
        "Trigger Time": "8\/8\/2018 9:30:00 AM"
    },
    {
        "Symbol": "OXBR",
        "Security Name": "Oxbridge Re Hldgs Ord Shares",
        "Market Category": "R",
        "Trigger Time": "8\/8\/2018 9:30:00 AM"
    },
    {
        "Symbol": "IFMK",
        "Security Name": "iFresh Inc. Cm St",
        "Market Category": "R",
        "Trigger Time": "8\/8\/2018 9:30:00 AM"
    },
    {
        "Symbol": "BECN",
        "Security Name": "Beacon Roofing Supply, Inc.",
        "Market Category": "Q",
        "Trigger Time": "8\/8\/2018 9:30:00 AM"
    },
    {
        "Symbol": "NIHD",
        "Security Name": "NII Holdings, Inc. Cmn Stk",
        "Market Category": "Q",
        "Trigger Time": "8\/8\/2018 9:30:00 AM"
    },
    {
        "Symbol": "RGNX",
        "Security Name": "REGENXBIO Inc. Cmn Stk",
        "Market Category": "Q",
        "Trigger Time": "8\/8\/2018 9:30:00 AM"
    },
    {
        "Symbol": "VYGR",
        "Security Name": "Voyager Therapeutics Cm St",
        "Market Category": "Q",
        "Trigger Time": "8\/8\/2018 9:30:00 AM"
    },
    {
        "Symbol": "EGLT",
        "Security Name": "Egalet Corporation",
        "Market Category": "R",
        "Trigger Time": "8\/8\/2018 9:30:00 AM"
    },
    {
        "Symbol": "RSLS",
        "Security Name": "ReShape Lifesciences Inc.",
        "Market Category": "R",
        "Trigger Time": "8\/8\/2018 9:30:00 AM"
    },
    {
        "Symbol": "CUTR",
        "Security Name": "Cutera Inc",
        "Market Category": "Q",
        "Trigger Time": "8\/8\/2018 9:30:00 AM"
    },
    {
        "Symbol": "TMDI",
        "Security Name": "Titan Medical Inc. Ord Shs",
        "Market Category": "R",
        "Trigger Time": "8\/8\/2018 9:30:00 AM"
    },
    {
        "Symbol": "EXTR",
        "Security Name": "Extreme Networks Inc",
        "Market Category": "Q",
        "Trigger Time": "8\/8\/2018 9:30:00 AM"
    },
    {
        "Symbol": "TWNK",
        "Security Name": "Hostess Brands Cl A Cmn Stk",
        "Market Category": "R",
        "Trigger Time": "8\/8\/2018 9:30:00 AM"
    },
    {
        "Symbol": "CHKE",
        "Security Name": "Cherokee Inc",
        "Market Category": "Q",
        "Trigger Time": "8\/8\/2018 9:30:00 AM"
    },
    {
        "Symbol": "PAVMW",
        "Security Name": "PAVmed Inc. Warrant",
        "Market Category": "R",
        "Trigger Time": "8\/8\/2018 9:30:00 AM"
    },
    {
        "Symbol": "HJLI",
        "Security Name": "Hancock Jaffe Laboratories Cmn",
        "Market Category": "R",
        "Trigger Time": "8\/8\/2018 9:30:00 AM"
    },
    {
        "Symbol": "NCSM",
        "Security Name": "NCS Multistage Holdings CM",
        "Market Category": "Q",
        "Trigger Time": "8\/8\/2018 9:30:01 AM"
    },
    {
        "Symbol": "AAXN",
        "Security Name": "Axon Enterprise Inc",
        "Market Category": "Q",
        "Trigger Time": "8\/8\/2018 9:30:01 AM"
    },
    {
        "Symbol": "DEPO",
        "Security Name": "Depomed, Inc.",
        "Market Category": "Q",
        "Trigger Time": "8\/8\/2018 9:30:02 AM"
    },
    {
        "Symbol": "ICON",
        "Security Name": "Iconix Brand Group, Inc.",
        "Market Category": "Q",
        "Trigger Time": "8\/8\/2018 9:30:03 AM"
    },
    {
        "Symbol": "EVOP",
        "Security Name": "EVO Payments, Inc. Cl A Cmn ",
        "Market Category": "Q",
        "Trigger Time": "8\/8\/2018 9:30:08 AM"
    },
    {
        "Symbol": "ROSEU",
        "Security Name": "Rosehill Resources Inc. Ut",
        "Market Category": "R",
        "Trigger Time": "8\/8\/2018 9:30:45 AM"
    },
    {
        "Symbol": "BBSI",
        "Security Name": "Barrett Business Services",
        "Market Category": "Q",
        "Trigger Time": "8\/8\/2018 9:30:46 AM"
    },
    {
        "Symbol": "UFCS",
        "Security Name": "United Fire Group, Inc",
        "Market Category": "Q",
        "Trigger Time": "8\/8\/2018 9:32:07 AM"
    },
    {
        "Symbol": "CETXW",
        "Security Name": "Cemtrex Inc. WTS",
        "Market Category": "R",
        "Trigger Time": "8\/8\/2018 9:32:12 AM"
    },
    {
        "Symbol": "TPIC",
        "Security Name": "TPI Composites CM",
        "Market Category": "Q",
        "Trigger Time": "8\/8\/2018 9:32:12 AM"
    },
    {
        "Symbol": "BOFI",
        "Security Name": "BofI Holding Inc",
        "Market Category": "Q",
        "Trigger Time": "8\/8\/2018 9:32:13 AM"
    },
    {
        "Symbol": "BLPH",
        "Security Name": "Bellerophon Thera Common Stock",
        "Market Category": "Q",
        "Trigger Time": "8\/8\/2018 9:32:17 AM"
    },
    {
        "Symbol": "ENTA",
        "Security Name": "Enanta Pharmaceuticals Inc",
        "Market Category": "Q",
        "Trigger Time": "8\/8\/2018 9:32:48 AM"
    },
    {
        "Symbol": "CKPT",
        "Security Name": "Checkpoint Therapeutics, CS",
        "Market Category": "R",
        "Trigger Time": "8\/8\/2018 9:34:05 AM"
    },
    {
        "Symbol": "NVMM",
        "Security Name": "Novume Solutions, Inc. Cm St",
        "Market Category": "R",
        "Trigger Time": "8\/8\/2018 9:35:11 AM"
    },
    {
        "Symbol": "SYNC",
        "Security Name": "Synacor, Inc.",
        "Market Category": "Q",
        "Trigger Time": "8\/8\/2018 9:35:59 AM"
    },
    {
        "Symbol": "CLNE",
        "Security Name": "Clean Energy Fuels Corp.",
        "Market Category": "Q",
        "Trigger Time": "8\/8\/2018 9:37:24 AM"
    },
    {
        "Symbol": "PULM",
        "Security Name": "Pulmatrix, Inc. Cmn Stk",
        "Market Category": "Q",
        "Trigger Time": "8\/8\/2018 9:39:45 AM"
    },
    {
        "Symbol": "CPST",
        "Security Name": "Capstone Turbine Corp",
        "Market Category": "R",
        "Trigger Time": "8\/8\/2018 9:40:14 AM"
    },
    {
        "Symbol": "AWRE",
        "Security Name": "Aware Inc",
        "Market Category": "Q",
        "Trigger Time": "8\/8\/2018 9:40:17 AM"
    },
    {
        "Symbol": "GEMP",
        "Security Name": "Gemphire Therapeutics CM",
        "Market Category": "Q",
        "Trigger Time": "8\/8\/2018 9:40:44 AM"
    },
    {
        "Symbol": "KOOL",
        "Security Name": "Cesca Therapeutics Inc.",
        "Market Category": "R",
        "Trigger Time": "8\/8\/2018 9:42:19 AM"
    },
    {
        "Symbol": "OHGI",
        "Security Name": "One Horizon Group Common Stk",
        "Market Category": "R",
        "Trigger Time": "8\/8\/2018 9:45:56 AM"
    },
    {
        "Symbol": "CTXR",
        "Security Name": "Citius Pharmaceuticals Cm St",
        "Market Category": "R",
        "Trigger Time": "8\/8\/2018 9:47:31 AM"
    },
    {
        "Symbol": "TTEC",
        "Security Name": "TTEC Holdings, Inc.",
        "Market Category": "Q",
        "Trigger Time": "8\/8\/2018 9:48:29 AM"
    },
    {
        "Symbol": "CYRXW",
        "Security Name": "CryoPort, Inc. Warrants",
        "Market Category": "R",
        "Trigger Time": "8\/8\/2018 9:49:52 AM"
    },
    {
        "Symbol": "MMDMR",
        "Security Name": "Modern Media Acquisition RT",
        "Market Category": "R",
        "Trigger Time": "8\/8\/2018 9:50:36 AM"
    },
    {
        "Symbol": "BASI",
        "Security Name": "Bioanalytical Systems Inc",
        "Market Category": "R",
        "Trigger Time": "8\/8\/2018 9:53:03 AM"
    },
    {
        "Symbol": "HJLIW",
        "Security Name": "Hancock Jaffe Laboratories Wts",
        "Market Category": "R",
        "Trigger Time": "8\/8\/2018 9:53:15 AM"
    },
    {
        "Symbol": "JG",
        "Security Name": "Aurora Mobile Limited ADS",
        "Market Category": "Q",
        "Trigger Time": "8\/8\/2018 9:53:18 AM"
    },
    {
        "Symbol": "ESTRW",
        "Security Name": "Estre Ambiental, Inc.",
        "Market Category": "Q",
        "Trigger Time": "8\/8\/2018 9:55:10 AM"
    },
    {
        "Symbol": "AVGR",
        "Security Name": "Avinger, Inc. ",
        "Market Category": "R",
        "Trigger Time": "8\/8\/2018 9:55:17 AM"
    },
    {
        "Symbol": "XOMA",
        "Security Name": "XOMA Corporation",
        "Market Category": "Q",
        "Trigger Time": "8\/8\/2018 10:03:09 AM"
    },
    {
        "Symbol": "ALRN",
        "Security Name": "Aileron Therapeutics, Inc. CS",
        "Market Category": "Q",
        "Trigger Time": "8\/8\/2018 10:04:36 AM"
    },
    {
        "Symbol": "NUROW",
        "Security Name": "NeuroMetrix, Inc. Wt",
        "Market Category": "R",
        "Trigger Time": "8\/8\/2018 10:05:31 AM"
    },
    {
        "Symbol": "ONSIW",
        "Security Name": "Oncobiologics, Inc. Ser A Wt",
        "Market Category": "R",
        "Trigger Time": "8\/8\/2018 10:07:04 AM"
    },
    {
        "Symbol": "PTIE",
        "Security Name": "Pain Therapeutics Inc",
        "Market Category": "Q",
        "Trigger Time": "8\/8\/2018 10:09:15 AM"
    },
    {
        "Symbol": "CYTXZ",
        "Security Name": "Cytori Therapeutics Srs S Wts",
        "Market Category": "R",
        "Trigger Time": "8\/8\/2018 10:15:04 AM"
    },
    {
        "Symbol": "WINS",
        "Security Name": "Wins Finance Hldgs Ord Shs",
        "Market Category": "R",
        "Trigger Time": "8\/8\/2018 10:18:28 AM"
    },
    {
        "Symbol": "EVFM",
        "Security Name": "Evofem Biosciences Inc Common",
        "Market Category": "R",
        "Trigger Time": "8\/8\/2018 10:20:07 AM"
    },
    {
        "Symbol": "CBLK",
        "Security Name": "Carbon Black, Inc. Cm St",
        "Market Category": "Q",
        "Trigger Time": "8\/8\/2018 10:20:34 AM"
    },
    {
        "Symbol": "GRNQ",
        "Security Name": "Greenpro Capital Corp. Cmn Stk",
        "Market Category": "R",
        "Trigger Time": "8\/8\/2018 10:27:21 AM"
    },
    {
        "Symbol": "CAR",
        "Security Name": "Avis Budget Group Cmn Stk",
        "Market Category": "Q",
        "Trigger Time": "8\/8\/2018 10:27:42 AM"
    },
    {
        "Symbol": "SUPN",
        "Security Name": "Supernus Pharmaceuticals, Inc.",
        "Market Category": "Q",
        "Trigger Time": "8\/8\/2018 10:35:15 AM"
    },
    {
        "Symbol": "BCACR",
        "Security Name": "Bison Cap Acquistion Cp Right",
        "Market Category": "R",
        "Trigger Time": "8\/8\/2018 10:57:37 AM"
    },
    {
        "Symbol": "FOSL",
        "Security Name": "Fossil Group, Inc. Common Stk",
        "Market Category": "Q",
        "Trigger Time": "8\/8\/2018 11:02:45 AM"
    },
    {
        "Symbol": "YECO",
        "Security Name": "Yulong Eco-Materials Ltd Ord",
        "Market Category": "R",
        "Trigger Time": "8\/8\/2018 11:03:01 AM"
    },
    {
        "Symbol": "SNSS",
        "Security Name": "Sunesis Pharmaceuticals Inc",
        "Market Category": "R",
        "Trigger Time": "8\/8\/2018 11:11:10 AM"
    },
    {
        "Symbol": "FWONK",
        "Security Name": "Liberty Formula One Cm Srs C",
        "Market Category": "Q",
        "Trigger Time": "8\/8\/2018 11:20:39 AM"
    },
    {
        "Symbol": "EYESW",
        "Security Name": "Second Sight Mdl Products Wt",
        "Market Category": "R",
        "Trigger Time": "8\/8\/2018 11:21:22 AM"
    },
    {
        "Symbol": "FWONA",
        "Security Name": "Liberty Formula One Cm Srs A",
        "Market Category": "Q",
        "Trigger Time": "8\/8\/2018 11:22:44 AM"
    },
    {
        "Symbol": "AKER",
        "Security Name": "Akers Biosciences Inc Cmn",
        "Market Category": "R",
        "Trigger Time": "8\/8\/2018 11:24:49 AM"
    },
    {
        "Symbol": "AKCA",
        "Security Name": "Akcea Therapeutics, Inc. CM",
        "Market Category": "Q",
        "Trigger Time": "8\/8\/2018 11:27:10 AM"
    },
    {
        "Symbol": "CLRBZ",
        "Security Name": "Cellectar Biosciences Sr A WT",
        "Market Category": "R",
        "Trigger Time": "8\/8\/2018 11:27:30 AM"
    },
    {
        "Symbol": "XSPA",
        "Security Name": "XpresSpa Group, Inc. ",
        "Market Category": "R",
        "Trigger Time": "8\/8\/2018 11:29:40 AM"
    },
    {
        "Symbol": "PRSC",
        "Security Name": "The Providence Service Corp",
        "Market Category": "Q",
        "Trigger Time": "8\/8\/2018 11:39:40 AM"
    },
    {
        "Symbol": "TYME",
        "Security Name": "Tyme Technologies, Inc. Cmn",
        "Market Category": "R",
        "Trigger Time": "8\/8\/2018 11:53:03 AM"
    },
    {
        "Symbol": "CHFS",
        "Security Name": "CHF Solutions, Inc.",
        "Market Category": "R",
        "Trigger Time": "8\/8\/2018 11:53:23 AM"
    },
    {
        "Symbol": "IMXIW",
        "Security Name": "Int'l Money Express Wt",
        "Market Category": "R",
        "Trigger Time": "8\/8\/2018 12:00:53 PM"
    },
    {
        "Symbol": "FLKS",
        "Security Name": "Flex Pharma, Inc. Cmn",
        "Market Category": "Q",
        "Trigger Time": "8\/8\/2018 12:07:56 PM"
    },
    {
        "Symbol": "LTRX",
        "Security Name": "Lantronix Inc",
        "Market Category": "R",
        "Trigger Time": "8\/8\/2018 12:33:58 PM"
    },
    {
        "Symbol": "CYTX",
        "Security Name": "Cytori Therapeutics Inc.",
        "Market Category": "R",
        "Trigger Time": "8\/8\/2018 12:39:27 PM"
    },
    {
        "Symbol": "ADXSW",
        "Security Name": "Advaxis, Inc. Warrants",
        "Market Category": "R",
        "Trigger Time": "8\/8\/2018 1:28:03 PM"
    },
    {
        "Symbol": "AXAS",
        "Security Name": "Abraxas Petroleum Corporation",
        "Market Category": "R",
        "Trigger Time": "8\/8\/2018 1:29:23 PM"
    },
    {
        "Symbol": "CSSE",
        "Security Name": "Chicken Sp for the Sl Cl A",
        "Market Category": "Q",
        "Trigger Time": "8\/8\/2018 1:33:19 PM"
    },
    {
        "Symbol": "HMNY",
        "Security Name": "Helios and Matheson Analytics",
        "Market Category": "R",
        "Trigger Time": "8\/8\/2018 1:35:26 PM"
    },
    {
        "Symbol": "CHMA",
        "Security Name": "Chiasma, Inc. Common Stk",
        "Market Category": "Q",
        "Trigger Time": "8\/8\/2018 1:42:21 PM"
    },
    {
        "Symbol": "SNOA",
        "Security Name": "Sonoma Pharmaceuticals",
        "Market Category": "R",
        "Trigger Time": "8\/8\/2018 1:47:04 PM"
    },
    {
        "Symbol": "KERX",
        "Security Name": "Keryx Biopharmaceuticals Inc",
        "Market Category": "R",
        "Trigger Time": "8\/8\/2018 1:51:22 PM"
    },
    {
        "Symbol": "INSM",
        "Security Name": "Insmed Inc.",
        "Market Category": "Q",
        "Trigger Time": "8\/8\/2018 2:24:13 PM"
    },
    {
        "Symbol": "RGLS",
        "Security Name": "Regulus Therapeutics Inc.",
        "Market Category": "Q",
        "Trigger Time": "8\/8\/2018 2:38:59 PM"
    },
    {
        "Symbol": "LONE",
        "Security Name": "Lonestar Resources US CM ST A",
        "Market Category": "Q",
        "Trigger Time": "8\/8\/2018 2:55:45 PM"
    },
    {
        "Symbol": "HAIR",
        "Security Name": "Restoration Robotics, Inc. CM",
        "Market Category": "Q",
        "Trigger Time": "8\/8\/2018 2:58:39 PM"
    },
    {
        "Symbol": "CTXRW",
        "Security Name": "Citius Pharmaceuticals Wt",
        "Market Category": "R",
        "Trigger Time": "8\/8\/2018 3:08:18 PM"
    },
    {
        "Symbol": "LINDW",
        "Security Name": "Lindblad Expeditions Hlds Wt",
        "Market Category": "R",
        "Trigger Time": "8\/8\/2018 3:10:30 PM"
    },
    {
        "Symbol": "BIOC",
        "Security Name": "Biocept Inc.",
        "Market Category": "R",
        "Trigger Time": "8\/8\/2018 3:20:17 PM"
    },
    {
        "Symbol": "JSYNR",
        "Security Name": "Jensyn Acquistion Corp. RT",
        "Market Category": "R",
        "Trigger Time": "8\/8\/2018 3:29:03 PM"
    },
    {
        "Symbol": "UMRX",
        "Security Name": "Unum Therapeutics Inc. CM",
        "Market Category": "Q",
        "Trigger Time": "8\/8\/2018 3:32:25 PM"
    },
    {
        "Symbol": "OTIC",
        "Security Name": "Otonomy, Inc.",
        "Market Category": "Q",
        "Trigger Time": "8\/8\/2018 3:32:37 PM"
    },
    {
        "Symbol": "MYNDW",
        "Security Name": "MYnd Analytics, Inc. Wt",
        "Market Category": "R",
        "Trigger Time": "8\/8\/2018 3:37:24 PM"
    },
    {
        "Symbol": "ARTX",
        "Security Name": "Arotech Corporation",
        "Market Category": "Q",
        "Trigger Time": "8\/8\/2018 3:46:26 PM"
    },
    {
        "Symbol": "QDEL",
        "Security Name": "Quidel Corp",
        "Market Category": "Q",
        "Trigger Time": "8\/8\/2018 3:47:43 PM"
    },
    {
        "Symbol": "IGLD",
        "Security Name": "Internet Gold-Gold Lines Ltd",
        "Market Category": "Q",
        "Trigger Time": "8\/8\/2018 3:59:14 PM"
    },
    {
        "Symbol": "INVE",
        "Security Name": "Identiv, Inc.",
        "Market Category": "R",
        "Trigger Time": "8\/8\/2018 3:59:25 PM"
    },
    {
        "Symbol": "BRQS",
        "Security Name": "Borqs Tech Inc Ord Shs",
        "Market Category": "R",
        "Trigger Time": "8\/8\/2018 3:59:50 PM"
    },
    {
        "Symbol": "PDCE",
        "Security Name": "PDC Energy, Inc.",
        "Market Category": "Q",
        "Trigger Time": "8\/9\/2018 9:30:00 AM"
    },
    {
        "Symbol": "MRAM",
        "Security Name": "Everspin Technologies COM",
        "Market Category": "Q",
        "Trigger Time": "8\/9\/2018 9:30:00 AM"
    },
    {
        "Symbol": "ABIL",
        "Security Name": "Ability Inc.",
        "Market Category": "R",
        "Trigger Time": "8\/9\/2018 9:30:00 AM"
    },
    {
        "Symbol": "SBPH",
        "Security Name": "Spring Bank Pharmaceuticals CS",
        "Market Category": "R",
        "Trigger Time": "8\/9\/2018 9:30:00 AM"
    },
    {
        "Symbol": "MNTA",
        "Security Name": "Momenta Pharmaceuticals Inc",
        "Market Category": "Q",
        "Trigger Time": "8\/9\/2018 9:30:00 AM"
    },
    {
        "Symbol": "UONEK",
        "Security Name": "Urban One, Inc.  Cl D",
        "Market Category": "R",
        "Trigger Time": "8\/9\/2018 9:30:00 AM"
    },
    {
        "Symbol": "GEVO",
        "Security Name": "Gevo, Inc. Common Stock",
        "Market Category": "R",
        "Trigger Time": "8\/9\/2018 9:30:00 AM"
    },
    {
        "Symbol": "AQMS",
        "Security Name": "Aqua Metals, Inc. Cm St",
        "Market Category": "R",
        "Trigger Time": "8\/9\/2018 9:30:00 AM"
    },
    {
        "Symbol": "PLXP",
        "Security Name": "PLx Pharma Inc.",
        "Market Category": "R",
        "Trigger Time": "8\/9\/2018 9:30:00 AM"
    },
    {
        "Symbol": "STMP",
        "Security Name": "Stamps.com Inc",
        "Market Category": "Q",
        "Trigger Time": "8\/9\/2018 9:30:00 AM"
    },
    {
        "Symbol": "PTLA",
        "Security Name": "Portola Pharmaceuticals Cmn St",
        "Market Category": "Q",
        "Trigger Time": "8\/9\/2018 9:30:00 AM"
    },
    {
        "Symbol": "FVE",
        "Security Name": "Five Star Senior Living Inc Cm",
        "Market Category": "R",
        "Trigger Time": "8\/9\/2018 9:30:00 AM"
    },
    {
        "Symbol": "ENG",
        "Security Name": "ENGlobal Corp Cmn Stk",
        "Market Category": "R",
        "Trigger Time": "8\/9\/2018 9:30:00 AM"
    },
    {
        "Symbol": "SOLO",
        "Security Name": "Electrameccanica Vehicles Cmn",
        "Market Category": "R",
        "Trigger Time": "8\/9\/2018 9:30:00 AM"
    },
    {
        "Symbol": "IPAS",
        "Security Name": "iPass Inc. Cmn Stk",
        "Market Category": "R",
        "Trigger Time": "8\/9\/2018 9:30:00 AM"
    },
    {
        "Symbol": "TTGT",
        "Security Name": "TechTarget, Inc.",
        "Market Category": "Q",
        "Trigger Time": "8\/9\/2018 9:30:00 AM"
    },
    {
        "Symbol": "MHLD",
        "Security Name": "Maiden Holdings, Ltd.",
        "Market Category": "Q",
        "Trigger Time": "8\/9\/2018 9:30:00 AM"
    },
    {
        "Symbol": "APEN",
        "Security Name": "Apollo Endosurgery, Inc. Cmn",
        "Market Category": "Q",
        "Trigger Time": "8\/9\/2018 9:30:00 AM"
    },
    {
        "Symbol": "WKHS",
        "Security Name": "Workhorse Group Common Stock",
        "Market Category": "R",
        "Trigger Time": "8\/9\/2018 9:30:00 AM"
    },
    {
        "Symbol": "RKDA",
        "Security Name": "Arcadia Biosciences, Inc. ",
        "Market Category": "R",
        "Trigger Time": "8\/9\/2018 9:30:00 AM"
    },
    {
        "Symbol": "TLGT",
        "Security Name": "Teligent, Inc. Common Stock",
        "Market Category": "Q",
        "Trigger Time": "8\/9\/2018 9:30:00 AM"
    },
    {
        "Symbol": "HDSN",
        "Security Name": "Hudson Technologies",
        "Market Category": "R",
        "Trigger Time": "8\/9\/2018 9:30:00 AM"
    },
    {
        "Symbol": "TCX",
        "Security Name": "Tucows Inc. Class A Conmon Stk",
        "Market Category": "R",
        "Trigger Time": "8\/9\/2018 9:30:01 AM"
    },
    {
        "Symbol": "SALM",
        "Security Name": "Salem Media Group, Inc. Cl A",
        "Market Category": "Q",
        "Trigger Time": "8\/9\/2018 9:30:01 AM"
    },
    {
        "Symbol": "NVCN",
        "Security Name": "Neovasc Inc. Cmn Shs",
        "Market Category": "R",
        "Trigger Time": "8\/9\/2018 9:30:01 AM"
    },
    {
        "Symbol": "APEI",
        "Security Name": "American Public Education, Inc",
        "Market Category": "Q",
        "Trigger Time": "8\/9\/2018 9:30:03 AM"
    },
    {
        "Symbol": "PRTS",
        "Security Name": "US Auto Parts Network Inc",
        "Market Category": "Q",
        "Trigger Time": "8\/9\/2018 9:30:03 AM"
    },
    {
        "Symbol": "UONE",
        "Security Name": "Urban One Inc Cl A",
        "Market Category": "R",
        "Trigger Time": "8\/9\/2018 9:30:03 AM"
    },
    {
        "Symbol": "SGRY",
        "Security Name": "Surgery Partners, Inc. CS",
        "Market Category": "Q",
        "Trigger Time": "8\/9\/2018 9:30:03 AM"
    },
    {
        "Symbol": "PCTI",
        "Security Name": "PC-Tel, Inc.",
        "Market Category": "Q",
        "Trigger Time": "8\/9\/2018 9:30:19 AM"
    },
    {
        "Symbol": "GLG",
        "Security Name": "China Commercial Credit, Inc.",
        "Market Category": "R",
        "Trigger Time": "8\/9\/2018 9:30:50 AM"
    },
    {
        "Symbol": "NVEE",
        "Security Name": "NV5 Global, Inc. Cmn Stk",
        "Market Category": "R",
        "Trigger Time": "8\/9\/2018 9:31:12 AM"
    },
    {
        "Symbol": "LJPC",
        "Security Name": "La Jolla Pharmctl Co Common",
        "Market Category": "R",
        "Trigger Time": "8\/9\/2018 9:31:16 AM"
    },
    {
        "Symbol": "UPL",
        "Security Name": "Ultra Petroleum Corp. Cmn Stk",
        "Market Category": "Q",
        "Trigger Time": "8\/9\/2018 9:31:54 AM"
    },
    {
        "Symbol": "ISSC",
        "Security Name": "Innovative Solutions & Support",
        "Market Category": "Q",
        "Trigger Time": "8\/9\/2018 9:33:48 AM"
    },
    {
        "Symbol": "AKBA",
        "Security Name": "Akebia Therapeutics, Inc. Cmn",
        "Market Category": "Q",
        "Trigger Time": "8\/9\/2018 9:34:10 AM"
    },
    {
        "Symbol": "RSLS",
        "Security Name": "ReShape Lifesciences Inc.",
        "Market Category": "R",
        "Trigger Time": "8\/9\/2018 9:34:45 AM"
    },
    {
        "Symbol": "DRIO",
        "Security Name": "DarioHealth Corp. Cmn Stk",
        "Market Category": "R",
        "Trigger Time": "8\/9\/2018 9:35:31 AM"
    },
    {
        "Symbol": "BLFS",
        "Security Name": "BioLife Solutions Inc Cmn Stk",
        "Market Category": "R",
        "Trigger Time": "8\/9\/2018 9:35:34 AM"
    },
    {
        "Symbol": "PEIX",
        "Security Name": "PACIFIC ETHANOL INC",
        "Market Category": "R",
        "Trigger Time": "8\/9\/2018 9:36:45 AM"
    },
    {
        "Symbol": "PIRS",
        "Security Name": "Pieris Pharma Cmn Stk",
        "Market Category": "R",
        "Trigger Time": "8\/9\/2018 9:44:51 AM"
    },
    {
        "Symbol": "ADXSW",
        "Security Name": "Advaxis, Inc. Warrants",
        "Market Category": "R",
        "Trigger Time": "8\/9\/2018 9:46:02 AM"
    },
    {
        "Symbol": "TCON",
        "Security Name": "TRACON Pharmaceutical Cmn Stk",
        "Market Category": "Q",
        "Trigger Time": "8\/9\/2018 9:47:30 AM"
    },
    {
        "Symbol": "CAAS",
        "Security Name": "China Automotive Systems, Inc.",
        "Market Category": "R",
        "Trigger Time": "8\/9\/2018 9:50:22 AM"
    },
    {
        "Symbol": "EGLT",
        "Security Name": "Egalet Corporation",
        "Market Category": "R",
        "Trigger Time": "8\/9\/2018 9:50:58 AM"
    },
    {
        "Symbol": "AMRWW",
        "Security Name": "Alta Mesa Resources, Inc. Wts",
        "Market Category": "R",
        "Trigger Time": "8\/9\/2018 9:52:24 AM"
    },
    {
        "Symbol": "SNGX",
        "Security Name": "Soligenix, Inc.",
        "Market Category": "R",
        "Trigger Time": "8\/9\/2018 9:52:55 AM"
    },
    {
        "Symbol": "IPIC",
        "Security Name": "iPic Entertainment Inc.CS",
        "Market Category": "Q",
        "Trigger Time": "8\/9\/2018 9:54:59 AM"
    },
    {
        "Symbol": "IFMK",
        "Security Name": "iFresh Inc. Cm St",
        "Market Category": "R",
        "Trigger Time": "8\/9\/2018 9:55:30 AM"
    },
    {
        "Symbol": "CLMT",
        "Security Name": "Calumet Specialty Products Par",
        "Market Category": "Q",
        "Trigger Time": "8\/9\/2018 9:58:48 AM"
    },
    {
        "Symbol": "MKGI",
        "Security Name": "Monaker Group CM",
        "Market Category": "R",
        "Trigger Time": "8\/9\/2018 10:02:11 AM"
    },
    {
        "Symbol": "PULM",
        "Security Name": "Pulmatrix, Inc. Cmn Stk",
        "Market Category": "Q",
        "Trigger Time": "8\/9\/2018 10:02:35 AM"
    },
    {
        "Symbol": "CATB",
        "Security Name": "Catabasis Pharmac. CM",
        "Market Category": "Q",
        "Trigger Time": "8\/9\/2018 10:05:32 AM"
    },
    {
        "Symbol": "SNOA",
        "Security Name": "Sonoma Pharmaceuticals",
        "Market Category": "R",
        "Trigger Time": "8\/9\/2018 10:07:50 AM"
    },
    {
        "Symbol": "ACST",
        "Security Name": "Acasti Pharma, Inc. Cl A Cmn",
        "Market Category": "R",
        "Trigger Time": "8\/9\/2018 10:09:10 AM"
    },
    {
        "Symbol": "KZIA",
        "Security Name": "Kazia Therapeutics Limited ADS",
        "Market Category": "R",
        "Trigger Time": "8\/9\/2018 10:10:02 AM"
    },
    {
        "Symbol": "LPTH",
        "Security Name": "LightPath Technologies Cl A",
        "Market Category": "R",
        "Trigger Time": "8\/9\/2018 10:14:55 AM"
    },
    {
        "Symbol": "JASNW",
        "Security Name": "Jason Industries, Inc. Warrant",
        "Market Category": "R",
        "Trigger Time": "8\/9\/2018 10:15:24 AM"
    },
    {
        "Symbol": "EYEGW",
        "Security Name": "Eyegate Pharmaceuticals Wts",
        "Market Category": "R",
        "Trigger Time": "8\/9\/2018 10:17:25 AM"
    },
    {
        "Symbol": "SRRA",
        "Security Name": "Sierra Oncology, Inc. Cmn",
        "Market Category": "Q",
        "Trigger Time": "8\/9\/2018 10:18:14 AM"
    },
    {
        "Symbol": "ADIL",
        "Security Name": "Adial Pharmaceuticals, Inc. Cm",
        "Market Category": "R",
        "Trigger Time": "8\/9\/2018 10:21:00 AM"
    },
    {
        "Symbol": "SAEX",
        "Security Name": "SAExploration Hldgs",
        "Market Category": "R",
        "Trigger Time": "8\/9\/2018 10:26:17 AM"
    },
    {
        "Symbol": "OSUR",
        "Security Name": "OraSure Technologies Inc",
        "Market Category": "Q",
        "Trigger Time": "8\/9\/2018 10:36:25 AM"
    },
    {
        "Symbol": "CALA",
        "Security Name": "Calithera Biosciences Com Stk",
        "Market Category": "Q",
        "Trigger Time": "8\/9\/2018 10:38:57 AM"
    },
    {
        "Symbol": "OPGNW",
        "Security Name": "OpGen, Inc. Warrant",
        "Market Category": "R",
        "Trigger Time": "8\/9\/2018 10:47:48 AM"
    },
    {
        "Symbol": "NVMM",
        "Security Name": "Novume Solutions, Inc. Cm St",
        "Market Category": "R",
        "Trigger Time": "8\/9\/2018 10:49:06 AM"
    },
    {
        "Symbol": "OHGI",
        "Security Name": "One Horizon Group Common Stk",
        "Market Category": "R",
        "Trigger Time": "8\/9\/2018 10:55:05 AM"
    },
    {
        "Symbol": "MPVD",
        "Security Name": "Mountain Province Diamd Cmn",
        "Market Category": "Q",
        "Trigger Time": "8\/9\/2018 10:57:41 AM"
    },
    {
        "Symbol": "MPAA",
        "Security Name": "Motorcar Parts & Accessories",
        "Market Category": "Q",
        "Trigger Time": "8\/9\/2018 11:05:35 AM"
    },
    {
        "Symbol": "OPESW",
        "Security Name": "Opes Acquisition WT",
        "Market Category": "R",
        "Trigger Time": "8\/9\/2018 11:06:42 AM"
    },
    {
        "Symbol": "FRTA",
        "Security Name": "Forterra Inc CM",
        "Market Category": "Q",
        "Trigger Time": "8\/9\/2018 11:07:38 AM"
    },
    {
        "Symbol": "RETA",
        "Security Name": "Reata Pharmaceuticals CLA CM",
        "Market Category": "Q",
        "Trigger Time": "8\/9\/2018 11:08:54 AM"
    },
    {
        "Symbol": "IEAWW",
        "Security Name": "Infrastructure & Enrgy Alt Wt",
        "Market Category": "R",
        "Trigger Time": "8\/9\/2018 11:09:48 AM"
    },
    {
        "Symbol": "FPRX",
        "Security Name": "Five Prime Therapeutics Cmn",
        "Market Category": "Q",
        "Trigger Time": "8\/9\/2018 11:16:31 AM"
    },
    {
        "Symbol": "FORK",
        "Security Name": "Fuling Global Inc. Ord Shares",
        "Market Category": "R",
        "Trigger Time": "8\/9\/2018 11:19:53 AM"
    },
    {
        "Symbol": "PRKR",
        "Security Name": "ParkerVision Inc",
        "Market Category": "R",
        "Trigger Time": "8\/9\/2018 11:20:12 AM"
    },
    {
        "Symbol": "OVAS",
        "Security Name": "OvaScience, Inc. Cmn Stk",
        "Market Category": "Q",
        "Trigger Time": "8\/9\/2018 11:33:58 AM"
    },
    {
        "Symbol": "ONSIW",
        "Security Name": "Oncobiologics, Inc. Ser A Wt",
        "Market Category": "R",
        "Trigger Time": "8\/9\/2018 11:34:54 AM"
    },
    {
        "Symbol": "NTES",
        "Security Name": "NetEase, Inc. American Dep Shs",
        "Market Category": "Q",
        "Trigger Time": "8\/9\/2018 11:35:33 AM"
    },
    {
        "Symbol": "CHFS",
        "Security Name": "CHF Solutions, Inc.",
        "Market Category": "R",
        "Trigger Time": "8\/9\/2018 11:42:32 AM"
    },
    {
        "Symbol": "CHEKZ",
        "Security Name": "Check-Cap Ltd. Sr C Wt",
        "Market Category": "R",
        "Trigger Time": "8\/9\/2018 11:43:05 AM"
    },
    {
        "Symbol": "HMNY",
        "Security Name": "Helios and Matheson Analytics",
        "Market Category": "R",
        "Trigger Time": "8\/9\/2018 11:48:33 AM"
    },
    {
        "Symbol": "CTMX",
        "Security Name": "CytomX Therapeutics, Inc. CS",
        "Market Category": "Q",
        "Trigger Time": "8\/9\/2018 11:51:38 AM"
    },
    {
        "Symbol": "WINS",
        "Security Name": "Wins Finance Hldgs Ord Shs",
        "Market Category": "R",
        "Trigger Time": "8\/9\/2018 11:54:31 AM"
    },
    {
        "Symbol": "FFBCW",
        "Security Name": "First Finan Bancorp Warrant",
        "Market Category": "Q",
        "Trigger Time": "8\/9\/2018 11:55:25 AM"
    },
    {
        "Symbol": "XSPA",
        "Security Name": "XpresSpa Group, Inc. ",
        "Market Category": "R",
        "Trigger Time": "8\/9\/2018 11:56:35 AM"
    },
    {
        "Symbol": "OASM",
        "Security Name": "Oasmia Pharmaceutical AB ADS",
        "Market Category": "R",
        "Trigger Time": "8\/9\/2018 12:02:04 PM"
    },
    {
        "Symbol": "JG",
        "Security Name": "Aurora Mobile Limited ADS",
        "Market Category": "Q",
        "Trigger Time": "8\/9\/2018 12:04:29 PM"
    },
    {
        "Symbol": "SUNW",
        "Security Name": "Sunworks, Inc. COM",
        "Market Category": "R",
        "Trigger Time": "8\/9\/2018 12:17:24 PM"
    },
    {
        "Symbol": "NLST",
        "Security Name": "Netlist, Inc.",
        "Market Category": "R",
        "Trigger Time": "8\/9\/2018 12:26:25 PM"
    },
    {
        "Symbol": "SRRK",
        "Security Name": "Scholar Rock Holding Corp CM",
        "Market Category": "Q",
        "Trigger Time": "8\/9\/2018 12:28:52 PM"
    },
    {
        "Symbol": "MTBC",
        "Security Name": "Medical Transcription Blng Cmn",
        "Market Category": "R",
        "Trigger Time": "8\/9\/2018 12:36:55 PM"
    },
    {
        "Symbol": "CBAK",
        "Security Name": "CBAK Energy Technology, Inc.",
        "Market Category": "Q",
        "Trigger Time": "8\/9\/2018 1:10:59 PM"
    },
    {
        "Symbol": "RIBTW",
        "Security Name": "RiceBran Technologies Warrant",
        "Market Category": "R",
        "Trigger Time": "8\/9\/2018 1:14:16 PM"
    },
    {
        "Symbol": "OHRP",
        "Security Name": "Ohr Pharmaceutical Inc Cmn Stk",
        "Market Category": "R",
        "Trigger Time": "8\/9\/2018 1:17:23 PM"
    },
    {
        "Symbol": "KBLMW",
        "Security Name": "KBL Merger Corp. IV WTS",
        "Market Category": "R",
        "Trigger Time": "8\/9\/2018 1:20:56 PM"
    },
    {
        "Symbol": "KBLMR",
        "Security Name": "KBL Merger Corp. IV RTS",
        "Market Category": "R",
        "Trigger Time": "8\/9\/2018 1:21:03 PM"
    },
    {
        "Symbol": "IMXIW",
        "Security Name": "Int'l Money Express Wt",
        "Market Category": "R",
        "Trigger Time": "8\/9\/2018 1:29:21 PM"
    },
    {
        "Symbol": "PRCP",
        "Security Name": "Perceptron Inc",
        "Market Category": "Q",
        "Trigger Time": "8\/9\/2018 1:33:39 PM"
    },
    {
        "Symbol": "ADILW",
        "Security Name": "Adial Pharmaceuticals Warrant",
        "Market Category": "R",
        "Trigger Time": "8\/9\/2018 1:40:14 PM"
    },
    {
        "Symbol": "TSRI",
        "Security Name": "TSR Inc",
        "Market Category": "R",
        "Trigger Time": "8\/9\/2018 1:44:57 PM"
    },
    {
        "Symbol": "SNMX",
        "Security Name": "Senomyx Inc",
        "Market Category": "Q",
        "Trigger Time": "8\/9\/2018 2:07:21 PM"
    },
    {
        "Symbol": "KBSF",
        "Security Name": "KBS Fashion Group Ltd",
        "Market Category": "R",
        "Trigger Time": "8\/9\/2018 2:12:45 PM"
    },
    {
        "Symbol": "BCACR",
        "Security Name": "Bison Cap Acquistion Cp Right",
        "Market Category": "R",
        "Trigger Time": "8\/9\/2018 2:15:30 PM"
    },
    {
        "Symbol": "SRTSW",
        "Security Name": "Sensus Healthcare WT",
        "Market Category": "R",
        "Trigger Time": "8\/9\/2018 2:22:31 PM"
    },
    {
        "Symbol": "ESES",
        "Security Name": "Eco-Stim Energy Sltns Cmn",
        "Market Category": "R",
        "Trigger Time": "8\/9\/2018 2:58:56 PM"
    },
    {
        "Symbol": "BKYI",
        "Security Name": "BIO-key International Cm St",
        "Market Category": "R",
        "Trigger Time": "8\/9\/2018 3:34:18 PM"
    },
    {
        "Symbol": "IPWR",
        "Security Name": "Ideal Power Inc.",
        "Market Category": "R",
        "Trigger Time": "8\/9\/2018 3:45:42 PM"
    },
    {
        "Symbol": "GDEN",
        "Security Name": "Golden Entertainment Inc",
        "Market Category": "Q",
        "Trigger Time": "8\/9\/2018 3:48:56 PM"
    },
    {
        "Symbol": "CHEKW",
        "Security Name": "Check-Cap Ltd. Srs A Wt",
        "Market Category": "R",
        "Trigger Time": "8\/9\/2018 3:55:36 PM"
    },
    {
        "Symbol": "OPNT",
        "Security Name": "Opiant Pharmaceuticals Cm St",
        "Market Category": "R",
        "Trigger Time": "8\/9\/2018 3:58:35 PM"
    }
]